{
  "node": {
    "458ebe3f127cd74715a746f118f0d6ef10c8ccc7": {
      "workers": {
        "app/page": "(sc_server)/./node_modules/next/dist/build/webpack/loaders/next-flight-action-entry-loader.js?actions=%5B%5B%22%2FUsers%2Fhumaidiridwan%2FDoshotz%2FDev%2FLearning-Playground%2FResfulAPI-Mock%2Factions%2FserverActions.ts%22%2C%5B%22addProduct%22%5D%5D%5D&__client_imported__=!"
      },
      "layer": {
        "app/page": "sc_server"
      }
    },
    "3b108cd3473de0cd5a9f071313358081b2b3ad32": {
      "workers": {
        "app/page": "(sc_server)/./node_modules/next/dist/build/webpack/loaders/next-flight-action-entry-loader.js?actions=%5B%5B%22%2FUsers%2Fhumaidiridwan%2FDoshotz%2FDev%2FLearning-Playground%2FResfulAPI-Mock%2Factions%2FserverActions.ts%22%2C%5B%22addProduct%22%5D%5D%5D&__client_imported__=!"
      },
      "layer": {
        "app/page": "sc_server"
      }
    }
  },
  "edge": {}
}